txtpresso/__init__.py
txtpresso/handlers.py
txtpresso/hello_world.py
txtpresso/server.py
txtpresso/utils.py
TXTpresso-0.1.8.dist-info/METADATA
TXTpresso-0.1.8.dist-info/WHEEL
TXTpresso-0.1.8.dist-info/entry_points.txt
TXTpresso-0.1.8.dist-info/top_level.txt
TXTpresso-0.1.8.dist-info/RECORD
