Metadata-Version: 2.1
Name: TXTpresso
Version: 0.1.8
Summary: A lightweight DNS-based message broker
Home-page: https://github.com/u1i/TXTpresso
Author: Uli Hitzel
Author-email: uli.hitzel@gmail.com
Classifier: Programming Language :: Python :: 3
Classifier: License :: OSI Approved :: MIT License
Classifier: Operating System :: OS Independent
Requires-Python: >=3.6
Requires-Dist: dnspython
Requires-Dist: dnslib
